Workbook

Sheet Dashboard
B2: =Settings!$C$4&" · Class Treasury"
B3: ="As of "&TEXT(TODAY(),"mmmm d, yyyy")&" · Goal: "&TEXT(Settings!$C$6,"$#,##0")&" by "&TEXT(Settings!$C$7,"mmmm yyyy")&" · Currently in "&IFERROR(LOOKUP(TODAY(),Settings!$C$14:$C$17,Settings!$B$14:$B$17),"Pre-MS1")
B5: CURRENT FUND | E5: GOAL BY MS4 | H5: PROGRESS TO GOAL | K5: NEEDED PER MONTH
B6: =(Settings!$C$5+SUM(Transactions!$I$5:$I$504)) | E6: =Settings!$C$6 | H6: =IF(Settings!$C$6=0,0,(Settings!$C$5+SUM(Transactions!$I$5:$I$504))/Settings!$C$6) | K6: =MAX(0,Settings!$C$6-(Settings!$C$5+SUM(Transactions!$I$5:$I$504)))/MAX(1,DATEDIF(TODAY(),MAX(TODAY(),Settings!$C$7),"m"))
B7: ="This month: "&TEXT((Calc!$C$17-Calc!$D$17),"+$#,##0;-$#,##0;$0") | E7: ="Deadline "&TEXT(Settings!$C$7,"mmm d, yyyy") | H7: =TEXT(MAX(0,Settings!$C$6-(Settings!$C$5+SUM(Transactions!$I$5:$I$504))),"$#,##0")&" still to go" | K7: =MAX(1,DATEDIF(TODAY(),MAX(TODAY(),Settings!$C$7),"m"))&" months left to hit the goal"
B9: TOTAL RAISED | E9: TOTAL SPENT | H9: PACE CHECK | K9: BEST FUNDRAISER
B10: =SUMIFS(Transactions!$E$5:$E$504,Transactions!$D$5:$D$504,"Income") | E10: =SUMIFS(Transactions!$E$5:$E$504,Transactions!$D$5:$D$504,"Expense") | H10: =IF((Settings!$C$5+SUM(Transactions!$I$5:$I$504))>=Calc!$F$17,"On Track","Behind Pace") | K10: =IFERROR(INDEX(Fundraisers!$B$6:$B$25,MATCH(1,Fundraisers!$G$6:$G$25,0)),"—")
B11: ="All-time, since "&TEXT(Settings!$C$14,"mmm yyyy") | E11: =IF(SUMIFS(Transactions!$E$5:$E$504,Transactions!$D$5:$D$504,"Income")=0,"",TEXT(SUMIFS(Transactions!$E$5:$E$504,Transactions!$D$5:$D$504,"Expense")/SUMIFS(Transactions!$E$5:$E$504,Transactions!$D$5:$D$504,"Income"),"0%")&" of everything raised") | H11: ="Target for today: "&TEXT(Calc!$F$17,"$#,##0") | K11: =IFERROR(TEXT(MAX(Fundraisers!$E$6:$E$25),"$#,##0")&" net profit","")
B13: Goal progress | C13: =REPT("█",ROUND(MAX(0,MIN(1,IF(Settings!$C$6=0,0,(Settings!$C$5+SUM(Transactions!$I$5:$I$504))/Settings!$C$6)))*60,0))&REPT("░",60-ROUND(MAX(0,MIN(1,IF(Settings!$C$6=0,0,(Settings!$C$5+SUM(Transactions!$I$5:$I$504))/Settings!$C$6)))*60,0)) | L13: =TEXT((Settings!$C$5+SUM(Transactions!$I$5:$I$504)),"$#,##0")&" / "&TEXT(Settings!$C$6,"$#,##0")
B15: Fund Balance vs. Goal Pace (last 12 months) | H15: Money In vs. Money Out (last 12 months)
B35: Where the Money Goes (all-time) | H35: Where the Money Comes From (all-time)
B54: Read-only view. The treasurer updates this file; figures recalculate automatically.

Sheet Transactions
A1: Transactions Log
A2: Add one row per deposit or payment, newest at the bottom. Fill the yellow columns; Type, Class Year, and Balance fill in automatically. Amounts are always positive.
A4: Date | B4: Description | C4: Category | D4: Type | E4: Amount | F4: Fundraiser / Event tag | G4: Notes / Receipt # | H4: Class Year | I4: +/- Amount | J4: Running Balance
A5: 45884 | B5: Dean's office class allocation | C5: School Allocation | D5: =IF(C5="","",IFERROR(INDEX(Settings!$C$21:$C$34,MATCH(C5,Settings!$B$21:$B$34,0)),"Check category")) | E5: 2000 | G5: Example row | H5: =IF(A5="","",IFERROR(LOOKUP(A5,Settings!$C$14:$C$17,Settings!$B$14:$B$17),"Pre-MS1")) | I5: =IF(OR(A5="",E5=""),0,IF(D5="Expense",-E5,E5)) | J5: =IF(A5="","",Settings!$C$5+SUM($I$5:I5))
A6: 45897 | B6: MS1 class dues | C6: Class Dues | D6: =IF(C6="","",IFERROR(INDEX(Settings!$C$21:$C$34,MATCH(C6,Settings!$B$21:$B$34,0)),"Check category")) | E6: 2400 | H6: =IF(A6="","",IFERROR(LOOKUP(A6,Settings!$C$14:$C$17,Settings!$B$14:$B$17),"Pre-MS1")) | I6: =IF(OR(A6="",E6=""),0,IF(D6="Expense",-E6,E6)) | J6: =IF(A6="","",Settings!$C$5+SUM($I$5:I6))
A7: 45912 | B7: Welcome mixer | C7: Social Events | D7: =IF(C7="","",IFERROR(INDEX(Settings!$C$21:$C$34,MATCH(C7,Settings!$B$21:$B$34,0)),"Check category")) | E7: 650 | H7: =IF(A7="","",IFERROR(LOOKUP(A7,Settings!$C$14:$C$17,Settings!$B$14:$B$17),"Pre-MS1")) | I7: =IF(OR(A7="",E7=""),0,IF(D7="Expense",-E7,E7)) | J7: =IF(A7="","",Settings!$C$5+SUM($I$5:I7))
A8: 45930 | B8: Class hoodie sales | C8: Fundraiser | D8: =IF(C8="","",IFERROR(INDEX(Settings!$C$21:$C$34,MATCH(C8,Settings!$B$21:$B$34,0)),"Check category")) | E8: 3100 | F8: Hoodie Sale | H8: =IF(A8="","",IFERROR(LOOKUP(A8,Settings!$C$14:$C$17,Settings!$B$14:$B$17),"Pre-MS1")) | I8: =IF(OR(A8="",E8=""),0,IF(D8="Expense",-E8,E8)) | J8: =IF(A8="","",Settings!$C$5+SUM($I$5:I8))
A9: 45930 | B9: Hoodie order | C9: Fundraiser Costs | D9: =IF(C9="","",IFERROR(INDEX(Settings!$C$21:$C$34,MATCH(C9,Settings!$B$21:$B$34,0)),"Check category")) | E9: 1850 | F9: Hoodie Sale | H9: =IF(A9="","",IFERROR(LOOKUP(A9,Settings!$C$14:$C$17,Settings!$B$14:$B$17),"Pre-MS1")) | I9: =IF(OR(A9="",E9=""),0,IF(D9="Expense",-E9,E9)) | J9: =IF(A9="","",Settings!$C$5+SUM($I$5:I9))
A10: 45955 | B10: Halloween party | C10: Social Events | D10: =IF(C10="","",IFERROR(INDEX(Settings!$C$21:$C$34,MATCH(C10,Settings!$B$21:$B$34,0)),"Check category")) | E10: 480 | H10: =IF(A10="","",IFERROR(LOOKUP(A10,Settings!$C$14:$C$17,Settings!$B$14:$B$17),"Pre-MS1")) | I10: =IF(OR(A10="",E10=""),0,IF(D10="Expense",-E10,E10)) | J10: =IF(A10="","",Settings!$C$5+SUM($I$5:I10))
A11: 45975 | B11: Bake sale | C11: Fundraiser | D11: =IF(C11="","",IFERROR(INDEX(Settings!$C$21:$C$34,MATCH(C11,Settings!$B$21:$B$34,0)),"Check category")) | E11: 420 | F11: Bake Sale | H11: =IF(A11="","",IFERROR(LOOKUP(A11,Settings!$C$14:$C$17,Settings!$B$14:$B$17),"Pre-MS1")) | I11: =IF(OR(A11="",E11=""),0,IF(D11="Expense",-E11,E11)) | J11: =IF(A11="","",Settings!$C$5+SUM($I$5:I11))
A12: 45975 | B12: Bake sale supplies | C12: Fundraiser Costs | D12: =IF(C12="","",IFERROR(INDEX(Settings!$C$21:$C$34,MATCH(C12,Settings!$B$21:$B$34,0)),"Check category")) | E12: 90 | F12: Bake Sale | H12: =IF(A12="","",IFERROR(LOOKUP(A12,Settings!$C$14:$C$17,Settings!$B$14:$B$17),"Pre-MS1")) | I12: =IF(OR(A12="",E12=""),0,IF(D12="Expense",-E12,E12)) | J12: =IF(A12="","",Settings!$C$5+SUM($I$5:I12))
A13: 46003 | B13: End-of-block celebration | C13: Food & Drinks | D13: =IF(C13="","",IFERROR(INDEX(Settings!$C$21:$C$34,MATCH(C13,Settings!$B$21:$B$34,0)),"Check category")) | E13: 380 | H13: =IF(A13="","",IFERROR(LOOKUP(A13,Settings!$C$14:$C$17,Settings!$B$14:$B$17),"Pre-MS1")) | I13: =IF(OR(A13="",E13=""),0,IF(D13="Expense",-E13,E13)) | J13: =IF(A13="","",Settings!$C$5+SUM($I$5:I13))
A14: 46042 | B14: Local clinic sponsorship | C14: Sponsorship | D14: =IF(C14="","",IFERROR(INDEX(Settings!$C$21:$C$34,MATCH(C14,Settings!$B$21:$B$34,0)),"Check category")) | E14: 1000 | H14: =IF(A14="","",IFERROR(LOOKUP(A14,Settings!$C$14:$C$17,Settings!$B$14:$B$17),"Pre-MS1")) | I14: =IF(OR(A14="",E14=""),0,IF(D14="Expense",-E14,E14)) | J14: =IF(A14="","",Settings!$C$5+SUM($I$5:I14))
A15: 46066 | B15: Valentine's grams | C15: Fundraiser | D15: =IF(C15="","",IFERROR(INDEX(Settings!$C$21:$C$34,MATCH(C15,Settings!$B$21:$B$34,0)),"Check category")) | E15: 310 | F15: Valentine Grams | H15: =IF(A15="","",IFERROR(LOOKUP(A15,Settings!$C$14:$C$17,Settings!$B$14:$B$17),"Pre-MS1")) | I15: =IF(OR(A15="",E15=""),0,IF(D15="Expense",-E15,E15)) | J15: =IF(A15="","",Settings!$C$5+SUM($I$5:I15))
A16: 46066 | B16: Valentine's grams supplies | C16: Fundraiser Costs | D16: =IF(C16="","",IFERROR(INDEX(Settings!$C$21:$C$34,MATCH(C16,Settings!$B$21:$B$34,0)),"Check category")) | E16: 60 | F16: Valentine Grams | H16: =IF(A16="","",IFERROR(LOOKUP(A16,Settings!$C$14:$C$17,Settings!$B$14:$B$17),"Pre-MS1")) | I16: =IF(OR(A16="",E16=""),0,IF(D16="Expense",-E16,E16)) | J16: =IF(A16="","",Settings!$C$5+SUM($I$5:I16))
A17: 46101 | B17: Post-exam social | C17: Social Events | D17: =IF(C17="","",IFERROR(INDEX(Settings!$C$21:$C$34,MATCH(C17,Settings!$B$21:$B$34,0)),"Check category")) | E17: 720 | H17: =IF(A17="","",IFERROR(LOOKUP(A17,Settings!$C$14:$C$17,Settings!$B$14:$B$17),"Pre-MS1")) | I17: =IF(OR(A17="",E17=""),0,IF(D17="Expense",-E17,E17)) | J17: =IF(A17="","",Settings!$C$5+SUM($I$5:I17))
A18: 46129 | B18: Trivia night tickets | C18: Fundraiser | D18: =IF(C18="","",IFERROR(INDEX(Settings!$C$21:$C$34,MATCH(C18,Settings!$B$21:$B$34,0)),"Check category")) | E18: 950 | F18: Trivia Night | H18: =IF(A18="","",IFERROR(LOOKUP(A18,Settings!$C$14:$C$17,Settings!$B$14:$B$17),"Pre-MS1")) | I18: =IF(OR(A18="",E18=""),0,IF(D18="Expense",-E18,E18)) | J18: =IF(A18="","",Settings!$C$5+SUM($I$5:I18))
A19: 46129 | B19: Trivia night venue & prizes | C19: Fundraiser Costs | D19: =IF(C19="","",IFERROR(INDEX(Settings!$C$21:$C$34,MATCH(C19,Settings!$B$21:$B$34,0)),"Check category")) | E19: 300 | F19: Trivia Night | H19: =IF(A19="","",IFERROR(LOOKUP(A19,Settings!$C$14:$C$17,Settings!$B$14:$B$17),"Pre-MS1")) | I19: =IF(OR(A19="",E19=""),0,IF(D19="Expense",-E19,E19)) | J19: =IF(A19="","",Settings!$C$5+SUM($I$5:I19))
A20: 46150 | B20: Faculty appreciation gifts | C20: Gifts & Awards | D20: =IF(C20="","",IFERROR(INDEX(Settings!$C$21:$C$34,MATCH(C20,Settings!$B$21:$B$34,0)),"Check category")) | E20: 250 | H20: =IF(A20="","",IFERROR(LOOKUP(A20,Settings!$C$14:$C$17,Settings!$B$14:$B$17),"Pre-MS1")) | I20: =IF(OR(A20="",E20=""),0,IF(D20="Expense",-E20,E20)) | J20: =IF(A20="","",Settings!$C$5+SUM($I$5:I20))
A21: 46178 | B21: End of MS1 banquet | C21: Milestone Events | D21: =IF(C21="","",IFERROR(INDEX(Settings!$C$21:$C$34,MATCH(C21,Settings!$B$21:$B$34,0)),"Check category")) | E21: 1400 | H21: =IF(A21="","",IFERROR(LOOKUP(A21,Settings!$C$14:$C$17,Settings!$B$14:$B$17),"Pre-MS1")) | I21: =IF(OR(A21="",E21=""),0,IF(D21="Expense",-E21,E21)) | J21: =IF(A21="","",Settings!$C$5+SUM($I$5:I21))
A22: 46255 | B22: MS2 class dues | C22: Class Dues | D22: =IF(C22="","",IFERROR(INDEX(Settings!$C$21:$C$34,MATCH(C22,Settings!$B$21:$B$34,0)),"Check category")) | E22: 2200 | H22: =IF(A22="","",IFERROR(LOOKUP(A22,Settings!$C$14:$C$17,Settings!$B$14:$B$17),"Pre-MS1")) | I22: =IF(OR(A22="",E22=""),0,IF(D22="Expense",-E22,E22)) | J22: =IF(A22="","",Settings!$C$5+SUM($I$5:I22))
A23: 46275 | B23: Welcome back BBQ | C23: Food & Drinks | D23: =IF(C23="","",IFERROR(INDEX(Settings!$C$21:$C$34,MATCH(C23,Settings!$B$21:$B$34,0)),"Check category")) | E23: 540 | H23: =IF(A23="","",IFERROR(LOOKUP(A23,Settings!$C$14:$C$17,Settings!$B$14:$B$17),"Pre-MS1")) | I23: =IF(OR(A23="",E23=""),0,IF(D23="Expense",-E23,E23)) | J23: =IF(A23="","",Settings!$C$5+SUM($I$5:I23))
A24: 46290 | B24: Class t-shirt sales | C24: Fundraiser | D24: =IF(C24="","",IFERROR(INDEX(Settings!$C$21:$C$34,MATCH(C24,Settings!$B$21:$B$34,0)),"Check category")) | E24: 1500 | F24: T-Shirt Sale | H24: =IF(A24="","",IFERROR(LOOKUP(A24,Settings!$C$14:$C$17,Settings!$B$14:$B$17),"Pre-MS1")) | I24: =IF(OR(A24="",E24=""),0,IF(D24="Expense",-E24,E24)) | J24: =IF(A24="","",Settings!$C$5+SUM($I$5:I24))
A25: 46290 | B25: T-shirt order | C25: Fundraiser Costs | D25: =IF(C25="","",IFERROR(INDEX(Settings!$C$21:$C$34,MATCH(C25,Settings!$B$21:$B$34,0)),"Check category")) | E25: 800 | F25: T-Shirt Sale | H25: =IF(A25="","",IFERROR(LOOKUP(A25,Settings!$C$14:$C$17,Settings!$B$14:$B$17),"Pre-MS1")) | I25: =IF(OR(A25="",E25=""),0,IF(D25="Expense",-E25,E25)) | J25: =IF(A25="","",Settings!$C$5+SUM($I$5:I25))
A26: 46304 | B26: Study break snacks | C26: Food & Drinks | D26: =IF(C26="","",IFERROR(INDEX(Settings!$C$21:$C$34,MATCH(C26,Settings!$B$21:$B$34,0)),"Check category")) | E26: 150 | H26: =IF(A26="","",IFERROR(LOOKUP(A26,Settings!$C$14:$C$17,Settings!$B$14:$B$17),"Pre-MS1")) | I26: =IF(OR(A26="",E26=""),0,IF(D26="Expense",-E26,E26)) | J26: =IF(A26="","",Settings!$C$5+SUM($I$5:I26))
A27: 46311 | B27: Alumni donation | C27: Donation | D27: =IF(C27="","",IFERROR(INDEX(Settings!$C$21:$C$34,MATCH(C27,Settings!$B$21:$B$34,0)),"Check category")) | E27: 500 | H27: =IF(A27="","",IFERROR(LOOKUP(A27,Settings!$C$14:$C$17,Settings!$B$14:$B$17),"Pre-MS1")) | I27: =IF(OR(A27="",E27=""),0,IF(D27="Expense",-E27,E27)) | J27: =IF(A27="","",Settings!$C$5+SUM($I$5:I27))
D28: =IF(C28="","",IFERROR(INDEX(Settings!$C$21:$C$34,MATCH(C28,Settings!$B$21:$B$34,0)),"Check category")) | H28: =IF(A28="","",IFERROR(LOOKUP(A28,Settings!$C$14:$C$17,Settings!$B$14:$B$17),"Pre-MS1")) | I28: =IF(OR(A28="",E28=""),0,IF(D28="Expense",-E28,E28)) | J28: =IF(A28="","",Settings!$C$5+SUM($I$5:I28))
D29: =IF(C29="","",IFERROR(INDEX(Settings!$C$21:$C$34,MATCH(C29,Settings!$B$21:$B$34,0)),"Check category")) | H29: =IF(A29="","",IFERROR(LOOKUP(A29,Settings!$C$14:$C$17,Settings!$B$14:$B$17),"Pre-MS1")) | I29: =IF(OR(A29="",E29=""),0,IF(D29="Expense",-E29,E29)) | J29: =IF(A29="","",Settings!$C$5+SUM($I$5:I29))
D30: =IF(C30="","",IFERROR(INDEX(Settings!$C$21:$C$34,MATCH(C30,Settings!$B$21:$B$34,0)),"Check category")) | H30: =IF(A30="","",IFERROR(LOOKUP(A30,Settings!$C$14:$C$17,Settings!$B$14:$B$17),"Pre-MS1")) | I30: =IF(OR(A30="",E30=""),0,IF(D30="Expense",-E30,E30)) | J30: =IF(A30="","",Settings!$C$5+SUM($I$5:I30))
D31: =IF(C31="","",IFERROR(INDEX(Settings!$C$21:$C$34,MATCH(C31,Settings!$B$21:$B$34,0)),"Check category")) | H31: =IF(A31="","",IFERROR(LOOKUP(A31,Settings!$C$14:$C$17,Settings!$B$14:$B$17),"Pre-MS1")) | I31: =IF(OR(A31="",E31=""),0,IF(D31="Expense",-E31,E31)) | J31: =IF(A31="","",Settings!$C$5+SUM($I$5:I31))
D32: =IF(C32="","",IFERROR(INDEX(Settings!$C$21:$C$34,MATCH(C32,Settings!$B$21:$B$34,0)),"Check category")) | H32: =IF(A32="","",IFERROR(LOOKUP(A32,Settings!$C$14:$C$17,Settings!$B$14:$B$17),"Pre-MS1")) | I32: =IF(OR(A32="",E32=""),0,IF(D32="Expense",-E32,E32)) | J32: =IF(A32="","",Settings!$C$5+SUM($I$5:I32))
D33: =IF(C33="","",IFERROR(INDEX(Settings!$C$21:$C$34,MATCH(C33,Settings!$B$21:$B$34,0)),"Check category")) | H33: =IF(A33="","",IFERROR(LOOKUP(A33,Settings!$C$14:$C$17,Settings!$B$14:$B$17),"Pre-MS1")) | I33: =IF(OR(A33="",E33=""),0,IF(D33="Expense",-E33,E33)) | J33: =IF(A33="","",Settings!$C$5+SUM($I$5:I33))
D34: =IF(C34="","",IFERROR(INDEX(Settings!$C$21:$C$34,MATCH(C34,Settings!$B$21:$B$34,0)),"Check category")) | H34: =IF(A34="","",IFERROR(LOOKUP(A34,Settings!$C$14:$C$17,Settings!$B$14:$B$17),"Pre-MS1")) | I34: =IF(OR(A34="",E34=""),0,IF(D34="Expense",-E34,E34)) | J34: =IF(A34="","",Settings!$C$5+SUM($I$5:I34))
D35: =IF(C35="","",IFERROR(INDEX(Settings!$C$21:$C$34,MATCH(C35,Settings!$B$21:$B$34,0)),"Check category")) | H35: =IF(A35="","",IFERROR(LOOKUP(A35,Settings!$C$14:$C$17,Settings!$B$14:$B$17),"Pre-MS1")) | I35: =IF(OR(A35="",E35=""),0,IF(D35="Expense",-E35,E35)) | J35: =IF(A35="","",Settings!$C$5+SUM($I$5:I35))
D36: =IF(C36="","",IFERROR(INDEX(Settings!$C$21:$C$34,MATCH(C36,Settings!$B$21:$B$34,0)),"Check category")) | H36: =IF(A36="","",IFERROR(LOOKUP(A36,Settings!$C$14:$C$17,Settings!$B$14:$B$17),"Pre-MS1")) | I36: =IF(OR(A36="",E36=""),0,IF(D36="Expense",-E36,E36)) | J36: =IF(A36="","",Settings!$C$5+SUM($I$5:I36))
D37: =IF(C37="","",IFERROR(INDEX(Settings!$C$21:$C$34,MATCH(C37,Settings!$B$21:$B$34,0)),"Check category")) | H37: =IF(A37="","",IFERROR(LOOKUP(A37,Settings!$C$14:$C$17,Settings!$B$14:$B$17),"Pre-MS1")) | I37: =IF(OR(A37="",E37=""),0,IF(D37="Expense",-E37,E37)) | J37: =IF(A37="","",Settings!$C$5+SUM($I$5:I37))
D38: =IF(C38="","",IFERROR(INDEX(Settings!$C$21:$C$34,MATCH(C38,Settings!$B$21:$B$34,0)),"Check category")) | H38: =IF(A38="","",IFERROR(LOOKUP(A38,Settings!$C$14:$C$17,Settings!$B$14:$B$17),"Pre-MS1")) | I38: =IF(OR(A38="",E38=""),0,IF(D38="Expense",-E38,E38)) | J38: =IF(A38="","",Settings!$C$5+SUM($I$5:I38))
D39: =IF(C39="","",IFERROR(INDEX(Settings!$C$21:$C$34,MATCH(C39,Settings!$B$21:$B$34,0)),"Check category")) | H39: =IF(A39="","",IFERROR(LOOKUP(A39,Settings!$C$14:$C$17,Settings!$B$14:$B$17),"Pre-MS1")) | I39: =IF(OR(A39="",E39=""),0,IF(D39="Expense",-E39,E39)) | J39: =IF(A39="","",Settings!$C$5+SUM($I$5:I39))
... D504: =IF(C504="","",IFERROR(INDEX(Settings!$C$21:$C$34,MATCH(C504,Settings!$B$21:$B$34,0)),"Check category")) | H504: =IF(A504="","",IFERROR(LOOKUP(A504,Settings!$C$14:$C$17,Settings!$B$14:$B$17),"Pre-MS1")) | I504: =IF(OR(A504="",E504=""),0,IF(D504="Expense",-E504,E504)) | J504: =IF(A504="","",Settings!$C$5+SUM($I$5:I504))

Sheet Fundraisers
B2: Fundraiser Scorecard
B3: Type each fundraiser's name exactly as used in the Transactions 'Fundraiser / Event tag' column. Revenue and costs pull in automatically.
B5: Fundraiser | C5: Revenue | D5: Costs | E5: Net Profit | F5: Margin | G5: Rank
B6: Hoodie Sale | C6: =IF(B6="","",SUMIFS(Transactions!$E$5:$E$504,Transactions!$F$5:$F$504,B6,Transactions!$D$5:$D$504,"Income")) | D6: =IF(B6="","",SUMIFS(Transactions!$E$5:$E$504,Transactions!$F$5:$F$504,B6,Transactions!$D$5:$D$504,"Expense")) | E6: =IF(B6="","",C6-D6) | F6: =IF(OR(B6="",N(C6)=0),"",E6/C6) | G6: =IF(B6="","",COUNTIFS($B$6:$B$25,"<>",$E$6:$E$25,">"&E6)+1)
B7: Bake Sale | C7: =IF(B7="","",SUMIFS(Transactions!$E$5:$E$504,Transactions!$F$5:$F$504,B7,Transactions!$D$5:$D$504,"Income")) | D7: =IF(B7="","",SUMIFS(Transactions!$E$5:$E$504,Transactions!$F$5:$F$504,B7,Transactions!$D$5:$D$504,"Expense")) | E7: =IF(B7="","",C7-D7) | F7: =IF(OR(B7="",N(C7)=0),"",E7/C7) | G7: =IF(B7="","",COUNTIFS($B$6:$B$25,"<>",$E$6:$E$25,">"&E7)+1)
B8: Valentine Grams | C8: =IF(B8="","",SUMIFS(Transactions!$E$5:$E$504,Transactions!$F$5:$F$504,B8,Transactions!$D$5:$D$504,"Income")) | D8: =IF(B8="","",SUMIFS(Transactions!$E$5:$E$504,Transactions!$F$5:$F$504,B8,Transactions!$D$5:$D$504,"Expense")) | E8: =IF(B8="","",C8-D8) | F8: =IF(OR(B8="",N(C8)=0),"",E8/C8) | G8: =IF(B8="","",COUNTIFS($B$6:$B$25,"<>",$E$6:$E$25,">"&E8)+1)
B9: Trivia Night | C9: =IF(B9="","",SUMIFS(Transactions!$E$5:$E$504,Transactions!$F$5:$F$504,B9,Transactions!$D$5:$D$504,"Income")) | D9: =IF(B9="","",SUMIFS(Transactions!$E$5:$E$504,Transactions!$F$5:$F$504,B9,Transactions!$D$5:$D$504,"Expense")) | E9: =IF(B9="","",C9-D9) | F9: =IF(OR(B9="",N(C9)=0),"",E9/C9) | G9: =IF(B9="","",COUNTIFS($B$6:$B$25,"<>",$E$6:$E$25,">"&E9)+1)
B10: T-Shirt Sale | C10: =IF(B10="","",SUMIFS(Transactions!$E$5:$E$504,Transactions!$F$5:$F$504,B10,Transactions!$D$5:$D$504,"Income")) | D10: =IF(B10="","",SUMIFS(Transactions!$E$5:$E$504,Transactions!$F$5:$F$504,B10,Transactions!$D$5:$D$504,"Expense")) | E10: =IF(B10="","",C10-D10) | F10: =IF(OR(B10="",N(C10)=0),"",E10/C10) | G10: =IF(B10="","",COUNTIFS($B$6:$B$25,"<>",$E$6:$E$25,">"&E10)+1)
C11: =IF(B11="","",SUMIFS(Transactions!$E$5:$E$504,Transactions!$F$5:$F$504,B11,Transactions!$D$5:$D$504,"Income")) | D11: =IF(B11="","",SUMIFS(Transactions!$E$5:$E$504,Transactions!$F$5:$F$504,B11,Transactions!$D$5:$D$504,"Expense")) | E11: =IF(B11="","",C11-D11) | F11: =IF(OR(B11="",N(C11)=0),"",E11/C11) | G11: =IF(B11="","",COUNTIFS($B$6:$B$25,"<>",$E$6:$E$25,">"&E11)+1)
C12: =IF(B12="","",SUMIFS(Transactions!$E$5:$E$504,Transactions!$F$5:$F$504,B12,Transactions!$D$5:$D$504,"Income")) | D12: =IF(B12="","",SUMIFS(Transactions!$E$5:$E$504,Transactions!$F$5:$F$504,B12,Transactions!$D$5:$D$504,"Expense")) | E12: =IF(B12="","",C12-D12) | F12: =IF(OR(B12="",N(C12)=0),"",E12/C12) | G12: =IF(B12="","",COUNTIFS($B$6:$B$25,"<>",$E$6:$E$25,">"&E12)+1)
C13: =IF(B13="","",SUMIFS(Transactions!$E$5:$E$504,Transactions!$F$5:$F$504,B13,Transactions!$D$5:$D$504,"Income")) | D13: =IF(B13="","",SUMIFS(Transactions!$E$5:$E$504,Transactions!$F$5:$F$504,B13,Transactions!$D$5:$D$504,"Expense")) | E13: =IF(B13="","",C13-D13) | F13: =IF(OR(B13="",N(C13)=0),"",E13/C13) | G13: =IF(B13="","",COUNTIFS($B$6:$B$25,"<>",$E$6:$E$25,">"&E13)+1)
C14: =IF(B14="","",SUMIFS(Transactions!$E$5:$E$504,Transactions!$F$5:$F$504,B14,Transactions!$D$5:$D$504,"Income")) | D14: =IF(B14="","",SUMIFS(Transactions!$E$5:$E$504,Transactions!$F$5:$F$504,B14,Transactions!$D$5:$D$504,"Expense")) | E14: =IF(B14="","",C14-D14) | F14: =IF(OR(B14="",N(C14)=0),"",E14/C14) | G14: =IF(B14="","",COUNTIFS($B$6:$B$25,"<>",$E$6:$E$25,">"&E14)+1)
C15: =IF(B15="","",SUMIFS(Transactions!$E$5:$E$504,Transactions!$F$5:$F$504,B15,Transactions!$D$5:$D$504,"Income")) | D15: =IF(B15="","",SUMIFS(Transactions!$E$5:$E$504,Transactions!$F$5:$F$504,B15,Transactions!$D$5:$D$504,"Expense")) | E15: =IF(B15="","",C15-D15) | F15: =IF(OR(B15="",N(C15)=0),"",E15/C15) | G15: =IF(B15="","",COUNTIFS($B$6:$B$25,"<>",$E$6:$E$25,">"&E15)+1)
C16: =IF(B16="","",SUMIFS(Transactions!$E$5:$E$504,Transactions!$F$5:$F$504,B16,Transactions!$D$5:$D$504,"Income")) | D16: =IF(B16="","",SUMIFS(Transactions!$E$5:$E$504,Transactions!$F$5:$F$504,B16,Transactions!$D$5:$D$504,"Expense")) | E16: =IF(B16="","",C16-D16) | F16: =IF(OR(B16="",N(C16)=0),"",E16/C16) | G16: =IF(B16="","",COUNTIFS($B$6:$B$25,"<>",$E$6:$E$25,">"&E16)+1)
C17: =IF(B17="","",SUMIFS(Transactions!$E$5:$E$504,Transactions!$F$5:$F$504,B17,Transactions!$D$5:$D$504,"Income")) | D17: =IF(B17="","",SUMIFS(Transactions!$E$5:$E$504,Transactions!$F$5:$F$504,B17,Transactions!$D$5:$D$504,"Expense")) | E17: =IF(B17="","",C17-D17) | F17: =IF(OR(B17="",N(C17)=0),"",E17/C17) | G17: =IF(B17="","",COUNTIFS($B$6:$B$25,"<>",$E$6:$E$25,">"&E17)+1)
C18: =IF(B18="","",SUMIFS(Transactions!$E$5:$E$504,Transactions!$F$5:$F$504,B18,Transactions!$D$5:$D$504,"Income")) | D18: =IF(B18="","",SUMIFS(Transactions!$E$5:$E$504,Transactions!$F$5:$F$504,B18,Transactions!$D$5:$D$504,"Expense")) | E18: =IF(B18="","",C18-D18) | F18: =IF(OR(B18="",N(C18)=0),"",E18/C18) | G18: =IF(B18="","",COUNTIFS($B$6:$B$25,"<>",$E$6:$E$25,">"&E18)+1)
C19: =IF(B19="","",SUMIFS(Transactions!$E$5:$E$504,Transactions!$F$5:$F$504,B19,Transactions!$D$5:$D$504,"Income")) | D19: =IF(B19="","",SUMIFS(Transactions!$E$5:$E$504,Transactions!$F$5:$F$504,B19,Transactions!$D$5:$D$504,"Expense")) | E19: =IF(B19="","",C19-D19) | F19: =IF(OR(B19="",N(C19)=0),"",E19/C19) | G19: =IF(B19="","",COUNTIFS($B$6:$B$25,"<>",$E$6:$E$25,">"&E19)+1)
C20: =IF(B20="","",SUMIFS(Transactions!$E$5:$E$504,Transactions!$F$5:$F$504,B20,Transactions!$D$5:$D$504,"Income")) | D20: =IF(B20="","",SUMIFS(Transactions!$E$5:$E$504,Transactions!$F$5:$F$504,B20,Transactions!$D$5:$D$504,"Expense")) | E20: =IF(B20="","",C20-D20) | F20: =IF(OR(B20="",N(C20)=0),"",E20/C20) | G20: =IF(B20="","",COUNTIFS($B$6:$B$25,"<>",$E$6:$E$25,">"&E20)+1)
C21: =IF(B21="","",SUMIFS(Transactions!$E$5:$E$504,Transactions!$F$5:$F$504,B21,Transactions!$D$5:$D$504,"Income")) | D21: =IF(B21="","",SUMIFS(Transactions!$E$5:$E$504,Transactions!$F$5:$F$504,B21,Transactions!$D$5:$D$504,"Expense")) | E21: =IF(B21="","",C21-D21) | F21: =IF(OR(B21="",N(C21)=0),"",E21/C21) | G21: =IF(B21="","",COUNTIFS($B$6:$B$25,"<>",$E$6:$E$25,">"&E21)+1)
C22: =IF(B22="","",SUMIFS(Transactions!$E$5:$E$504,Transactions!$F$5:$F$504,B22,Transactions!$D$5:$D$504,"Income")) | D22: =IF(B22="","",SUMIFS(Transactions!$E$5:$E$504,Transactions!$F$5:$F$504,B22,Transactions!$D$5:$D$504,"Expense")) | E22: =IF(B22="","",C22-D22) | F22: =IF(OR(B22="",N(C22)=0),"",E22/C22) | G22: =IF(B22="","",COUNTIFS($B$6:$B$25,"<>",$E$6:$E$25,">"&E22)+1)
... C25: =IF(B25="","",SUMIFS(Transactions!$E$5:$E$504,Transactions!$F$5:$F$504,B25,Transactions!$D$5:$D$504,"Income")) | D25: =IF(B25="","",SUMIFS(Transactions!$E$5:$E$504,Transactions!$F$5:$F$504,B25,Transactions!$D$5:$D$504,"Expense")) | E25: =IF(B25="","",C25-D25) | F25: =IF(OR(B25="",N(C25)=0),"",E25/C25) | G25: =IF(B25="","",COUNTIFS($B$6:$B$25,"<>",$E$6:$E$25,">"&E25)+1)
B26: Total | C26: =SUM(C6:C25) | D26: =SUM(D6:D25) | E26: =SUM(E6:E25)

Sheet Budget
B2: Spending Budget
B3: Pick a class year, then set a budget per category. Actuals pull from Transactions.
B5: Class year | C5: MS2
B7: Category | C7: Budget | D7: Actual | E7: Remaining | F7: % Used | G7: Status
B8: =Settings!$B$27 | C8: 1500 | D8: =SUMIFS(Transactions!$E$5:$E$504,Transactions!$C$5:$C$504,B8,Transactions!$H$5:$H$504,$C$5,Transactions!$D$5:$D$504,"Expense") | E8: =C8-D8 | F8: =IF(C8=0,0,D8/C8) | G8: =IF(C8=0,"",IF(F8>1,"Over budget",IF(F8>=0.8,"Watch","OK")))
B9: =Settings!$B$28 | C9: 2000 | D9: =SUMIFS(Transactions!$E$5:$E$504,Transactions!$C$5:$C$504,B9,Transactions!$H$5:$H$504,$C$5,Transactions!$D$5:$D$504,"Expense") | E9: =C9-D9 | F9: =IF(C9=0,0,D9/C9) | G9: =IF(C9=0,"",IF(F9>1,"Over budget",IF(F9>=0.8,"Watch","OK")))
B10: =Settings!$B$29 | C10: 1200 | D10: =SUMIFS(Transactions!$E$5:$E$504,Transactions!$C$5:$C$504,B10,Transactions!$H$5:$H$504,$C$5,Transactions!$D$5:$D$504,"Expense") | E10: =C10-D10 | F10: =IF(C10=0,0,D10/C10) | G10: =IF(C10=0,"",IF(F10>1,"Over budget",IF(F10>=0.8,"Watch","OK")))
B11: =Settings!$B$30 | C11: 500 | D11: =SUMIFS(Transactions!$E$5:$E$504,Transactions!$C$5:$C$504,B11,Transactions!$H$5:$H$504,$C$5,Transactions!$D$5:$D$504,"Expense") | E11: =C11-D11 | F11: =IF(C11=0,0,D11/C11) | G11: =IF(C11=0,"",IF(F11>1,"Over budget",IF(F11>=0.8,"Watch","OK")))
B12: =Settings!$B$31 | C12: 1500 | D12: =SUMIFS(Transactions!$E$5:$E$504,Transactions!$C$5:$C$504,B12,Transactions!$H$5:$H$504,$C$5,Transactions!$D$5:$D$504,"Expense") | E12: =C12-D12 | F12: =IF(C12=0,0,D12/C12) | G12: =IF(C12=0,"",IF(F12>1,"Over budget",IF(F12>=0.8,"Watch","OK")))
B13: =Settings!$B$32 | C13: 200 | D13: =SUMIFS(Transactions!$E$5:$E$504,Transactions!$C$5:$C$504,B13,Transactions!$H$5:$H$504,$C$5,Transactions!$D$5:$D$504,"Expense") | E13: =C13-D13 | F13: =IF(C13=0,0,D13/C13) | G13: =IF(C13=0,"",IF(F13>1,"Over budget",IF(F13>=0.8,"Watch","OK")))
B14: =Settings!$B$33 | C14: 400 | D14: =SUMIFS(Transactions!$E$5:$E$504,Transactions!$C$5:$C$504,B14,Transactions!$H$5:$H$504,$C$5,Transactions!$D$5:$D$504,"Expense") | E14: =C14-D14 | F14: =IF(C14=0,0,D14/C14) | G14: =IF(C14=0,"",IF(F14>1,"Over budget",IF(F14>=0.8,"Watch","OK")))
B15: =Settings!$B$34 | C15: 300 | D15: =SUMIFS(Transactions!$E$5:$E$504,Transactions!$C$5:$C$504,B15,Transactions!$H$5:$H$504,$C$5,Transactions!$D$5:$D$504,"Expense") | E15: =C15-D15 | F15: =IF(C15=0,0,D15/C15) | G15: =IF(C15=0,"",IF(F15>1,"Over budget",IF(F15>=0.8,"Watch","OK")))
B16: Total | C16: =SUM(C8:C15) | D16: =SUM(D8:D15) | E16: =SUM(E8:E15) | F16: =IF(C16=0,0,D16/C16)

Sheet Settings
B2: Settings | F2: Yellow cells with blue text are inputs. Everything else is calculated.
B4: Class name | C4: Class of 2029 | F4: Shown as the dashboard title.
B5: Starting balance | C5: 0 | F5: Money in the account before the first transaction logged.
B6: Savings goal | C6: 15000 | F6: Target fund balance by the goal deadline (MS4).
B7: Goal deadline | C7: 47239 | F7: Date the goal should be reached.
B12: Class years & milestones
B13: Year | C13: Start date | D13: End date | E13: Milestone (% of goal by year end)
B14: MS1 | C14: 45870 | D14: 46234 | E14: 0.25 | F14: Dates decide which class year each transaction counts toward.
B15: MS2 | C15: 46235 | D15: 46599 | E15: 0.5 | F15: Milestones set the year-end target balance on the dashboard.
B16: MS3 | C16: 46600 | D16: 46965 | E16: 0.75
B17: MS4 | C17: 46966 | D17: 47269 | E17: 1
B19: Categories
B20: Category | C20: Type
B21: Class Dues | C21: Income | F21: Rename categories freely. Type must be Income or Expense.
B22: Fundraiser | C22: Income | F22: Milestone Events = White Coat, Match Day, graduation, etc.
B23: Sponsorship | C23: Income
B24: School Allocation | C24: Income
B25: Donation | C25: Income
B26: Other Income | C26: Income
B27: Social Events | C27: Expense
B28: Milestone Events | C28: Expense
B29: Food & Drinks | C29: Expense
B30: Class Merchandise | C30: Expense
B31: Fundraiser Costs | C31: Expense
B32: Supplies & Printing | C32: Expense
B33: Gifts & Awards | C33: Expense
B34: Other Expense | C34: Expense

Sheet Calc
A1: Helper calculations for dashboard charts. Do not edit.
A3: Current month | B3: =DATE(YEAR(TODAY()),MONTH(TODAY()),1)
A5: Month | B5: Label | C5: Money In | D5: Money Out | E5: Fund Balance | F5: On-Pace Target
A6: =EDATE($B$3,-11) | B6: =TEXT(A6,"mmm yy") | C6: =SUMIFS(Transactions!$E$5:$E$504,Transactions!$D$5:$D$504,"Income",Transactions!$A$5:$A$504,">="&A6,Transactions!$A$5:$A$504,"<"&EDATE(A6,1)) | D6: =SUMIFS(Transactions!$E$5:$E$504,Transactions!$D$5:$D$504,"Expense",Transactions!$A$5:$A$504,">="&A6,Transactions!$A$5:$A$504,"<"&EDATE(A6,1)) | E6: =Settings!$C$5+SUMIFS(Transactions!$I$5:$I$504,Transactions!$A$5:$A$504,"<"&EDATE(A6,1)) | F6: =MAX(Settings!$C$5,MIN(Settings!$C$6,Settings!$C$5+(Settings!$C$6-Settings!$C$5)*MAX(0,MIN(EDATE(A6,1),TODAY()+1)-Settings!$C$14)/(Settings!$C$7-Settings!$C$14)))
A7: =EDATE($B$3,-10) | B7: =TEXT(A7,"mmm yy") | C7: =SUMIFS(Transactions!$E$5:$E$504,Transactions!$D$5:$D$504,"Income",Transactions!$A$5:$A$504,">="&A7,Transactions!$A$5:$A$504,"<"&EDATE(A7,1)) | D7: =SUMIFS(Transactions!$E$5:$E$504,Transactions!$D$5:$D$504,"Expense",Transactions!$A$5:$A$504,">="&A7,Transactions!$A$5:$A$504,"<"&EDATE(A7,1)) | E7: =Settings!$C$5+SUMIFS(Transactions!$I$5:$I$504,Transactions!$A$5:$A$504,"<"&EDATE(A7,1)) | F7: =MAX(Settings!$C$5,MIN(Settings!$C$6,Settings!$C$5+(Settings!$C$6-Settings!$C$5)*MAX(0,MIN(EDATE(A7,1),TODAY()+1)-Settings!$C$14)/(Settings!$C$7-Settings!$C$14)))
A8: =EDATE($B$3,-9) | B8: =TEXT(A8,"mmm yy") | C8: =SUMIFS(Transactions!$E$5:$E$504,Transactions!$D$5:$D$504,"Income",Transactions!$A$5:$A$504,">="&A8,Transactions!$A$5:$A$504,"<"&EDATE(A8,1)) | D8: =SUMIFS(Transactions!$E$5:$E$504,Transactions!$D$5:$D$504,"Expense",Transactions!$A$5:$A$504,">="&A8,Transactions!$A$5:$A$504,"<"&EDATE(A8,1)) | E8: =Settings!$C$5+SUMIFS(Transactions!$I$5:$I$504,Transactions!$A$5:$A$504,"<"&EDATE(A8,1)) | F8: =MAX(Settings!$C$5,MIN(Settings!$C$6,Settings!$C$5+(Settings!$C$6-Settings!$C$5)*MAX(0,MIN(EDATE(A8,1),TODAY()+1)-Settings!$C$14)/(Settings!$C$7-Settings!$C$14)))
A9: =EDATE($B$3,-8) | B9: =TEXT(A9,"mmm yy") | C9: =SUMIFS(Transactions!$E$5:$E$504,Transactions!$D$5:$D$504,"Income",Transactions!$A$5:$A$504,">="&A9,Transactions!$A$5:$A$504,"<"&EDATE(A9,1)) | D9: =SUMIFS(Transactions!$E$5:$E$504,Transactions!$D$5:$D$504,"Expense",Transactions!$A$5:$A$504,">="&A9,Transactions!$A$5:$A$504,"<"&EDATE(A9,1)) | E9: =Settings!$C$5+SUMIFS(Transactions!$I$5:$I$504,Transactions!$A$5:$A$504,"<"&EDATE(A9,1)) | F9: =MAX(Settings!$C$5,MIN(Settings!$C$6,Settings!$C$5+(Settings!$C$6-Settings!$C$5)*MAX(0,MIN(EDATE(A9,1),TODAY()+1)-Settings!$C$14)/(Settings!$C$7-Settings!$C$14)))
A10: =EDATE($B$3,-7) | B10: =TEXT(A10,"mmm yy") | C10: =SUMIFS(Transactions!$E$5:$E$504,Transactions!$D$5:$D$504,"Income",Transactions!$A$5:$A$504,">="&A10,Transactions!$A$5:$A$504,"<"&EDATE(A10,1)) | D10: =SUMIFS(Transactions!$E$5:$E$504,Transactions!$D$5:$D$504,"Expense",Transactions!$A$5:$A$504,">="&A10,Transactions!$A$5:$A$504,"<"&EDATE(A10,1)) | E10: =Settings!$C$5+SUMIFS(Transactions!$I$5:$I$504,Transactions!$A$5:$A$504,"<"&EDATE(A10,1)) | F10: =MAX(Settings!$C$5,MIN(Settings!$C$6,Settings!$C$5+(Settings!$C$6-Settings!$C$5)*MAX(0,MIN(EDATE(A10,1),TODAY()+1)-Settings!$C$14)/(Settings!$C$7-Settings!$C$14)))
A11: =EDATE($B$3,-6) | B11: =TEXT(A11,"mmm yy") | C11: =SUMIFS(Transactions!$E$5:$E$504,Transactions!$D$5:$D$504,"Income",Transactions!$A$5:$A$504,">="&A11,Transactions!$A$5:$A$504,"<"&EDATE(A11,1)) | D11: =SUMIFS(Transactions!$E$5:$E$504,Transactions!$D$5:$D$504,"Expense",Transactions!$A$5:$A$504,">="&A11,Transactions!$A$5:$A$504,"<"&EDATE(A11,1)) | E11: =Settings!$C$5+SUMIFS(Transactions!$I$5:$I$504,Transactions!$A$5:$A$504,"<"&EDATE(A11,1)) | F11: =MAX(Settings!$C$5,MIN(Settings!$C$6,Settings!$C$5+(Settings!$C$6-Settings!$C$5)*MAX(0,MIN(EDATE(A11,1),TODAY()+1)-Settings!$C$14)/(Settings!$C$7-Settings!$C$14)))
A12: =EDATE($B$3,-5) | B12: =TEXT(A12,"mmm yy") | C12: =SUMIFS(Transactions!$E$5:$E$504,Transactions!$D$5:$D$504,"Income",Transactions!$A$5:$A$504,">="&A12,Transactions!$A$5:$A$504,"<"&EDATE(A12,1)) | D12: =SUMIFS(Transactions!$E$5:$E$504,Transactions!$D$5:$D$504,"Expense",Transactions!$A$5:$A$504,">="&A12,Transactions!$A$5:$A$504,"<"&EDATE(A12,1)) | E12: =Settings!$C$5+SUMIFS(Transactions!$I$5:$I$504,Transactions!$A$5:$A$504,"<"&EDATE(A12,1)) | F12: =MAX(Settings!$C$5,MIN(Settings!$C$6,Settings!$C$5+(Settings!$C$6-Settings!$C$5)*MAX(0,MIN(EDATE(A12,1),TODAY()+1)-Settings!$C$14)/(Settings!$C$7-Settings!$C$14)))
A13: =EDATE($B$3,-4) | B13: =TEXT(A13,"mmm yy") | C13: =SUMIFS(Transactions!$E$5:$E$504,Transactions!$D$5:$D$504,"Income",Transactions!$A$5:$A$504,">="&A13,Transactions!$A$5:$A$504,"<"&EDATE(A13,1)) | D13: =SUMIFS(Transactions!$E$5:$E$504,Transactions!$D$5:$D$504,"Expense",Transactions!$A$5:$A$504,">="&A13,Transactions!$A$5:$A$504,"<"&EDATE(A13,1)) | E13: =Settings!$C$5+SUMIFS(Transactions!$I$5:$I$504,Transactions!$A$5:$A$504,"<"&EDATE(A13,1)) | F13: =MAX(Settings!$C$5,MIN(Settings!$C$6,Settings!$C$5+(Settings!$C$6-Settings!$C$5)*MAX(0,MIN(EDATE(A13,1),TODAY()+1)-Settings!$C$14)/(Settings!$C$7-Settings!$C$14)))
A14: =EDATE($B$3,-3) | B14: =TEXT(A14,"mmm yy") | C14: =SUMIFS(Transactions!$E$5:$E$504,Transactions!$D$5:$D$504,"Income",Transactions!$A$5:$A$504,">="&A14,Transactions!$A$5:$A$504,"<"&EDATE(A14,1)) | D14: =SUMIFS(Transactions!$E$5:$E$504,Transactions!$D$5:$D$504,"Expense",Transactions!$A$5:$A$504,">="&A14,Transactions!$A$5:$A$504,"<"&EDATE(A14,1)) | E14: =Settings!$C$5+SUMIFS(Transactions!$I$5:$I$504,Transactions!$A$5:$A$504,"<"&EDATE(A14,1)) | F14: =MAX(Settings!$C$5,MIN(Settings!$C$6,Settings!$C$5+(Settings!$C$6-Settings!$C$5)*MAX(0,MIN(EDATE(A14,1),TODAY()+1)-Settings!$C$14)/(Settings!$C$7-Settings!$C$14)))
A15: =EDATE($B$3,-2) | B15: =TEXT(A15,"mmm yy") | C15: =SUMIFS(Transactions!$E$5:$E$504,Transactions!$D$5:$D$504,"Income",Transactions!$A$5:$A$504,">="&A15,Transactions!$A$5:$A$504,"<"&EDATE(A15,1)) | D15: =SUMIFS(Transactions!$E$5:$E$504,Transactions!$D$5:$D$504,"Expense",Transactions!$A$5:$A$504,">="&A15,Transactions!$A$5:$A$504,"<"&EDATE(A15,1)) | E15: =Settings!$C$5+SUMIFS(Transactions!$I$5:$I$504,Transactions!$A$5:$A$504,"<"&EDATE(A15,1)) | F15: =MAX(Settings!$C$5,MIN(Settings!$C$6,Settings!$C$5+(Settings!$C$6-Settings!$C$5)*MAX(0,MIN(EDATE(A15,1),TODAY()+1)-Settings!$C$14)/(Settings!$C$7-Settings!$C$14)))
A16: =EDATE($B$3,-1) | B16: =TEXT(A16,"mmm yy") | C16: =SUMIFS(Transactions!$E$5:$E$504,Transactions!$D$5:$D$504,"Income",Transactions!$A$5:$A$504,">="&A16,Transactions!$A$5:$A$504,"<"&EDATE(A16,1)) | D16: =SUMIFS(Transactions!$E$5:$E$504,Transactions!$D$5:$D$504,"Expense",Transactions!$A$5:$A$504,">="&A16,Transactions!$A$5:$A$504,"<"&EDATE(A16,1)) | E16: =Settings!$C$5+SUMIFS(Transactions!$I$5:$I$504,Transactions!$A$5:$A$504,"<"&EDATE(A16,1)) | F16: =MAX(Settings!$C$5,MIN(Settings!$C$6,Settings!$C$5+(Settings!$C$6-Settings!$C$5)*MAX(0,MIN(EDATE(A16,1),TODAY()+1)-Settings!$C$14)/(Settings!$C$7-Settings!$C$14)))
A17: =EDATE($B$3,0) | B17: =TEXT(A17,"mmm yy") | C17: =SUMIFS(Transactions!$E$5:$E$504,Transactions!$D$5:$D$504,"Income",Transactions!$A$5:$A$504,">="&A17,Transactions!$A$5:$A$504,"<"&EDATE(A17,1)) | D17: =SUMIFS(Transactions!$E$5:$E$504,Transactions!$D$5:$D$504,"Expense",Transactions!$A$5:$A$504,">="&A17,Transactions!$A$5:$A$504,"<"&EDATE(A17,1)) | E17: =Settings!$C$5+SUMIFS(Transactions!$I$5:$I$504,Transactions!$A$5:$A$504,"<"&EDATE(A17,1)) | F17: =MAX(Settings!$C$5,MIN(Settings!$C$6,Settings!$C$5+(Settings!$C$6-Settings!$C$5)*MAX(0,MIN(EDATE(A17,1),TODAY()+1)-Settings!$C$14)/(Settings!$C$7-Settings!$C$14)))
A20: Spending category | B20: All-time
A21: =Settings!$B$27 | B21: =SUMIFS(Transactions!$E$5:$E$504,Transactions!$C$5:$C$504,A21,Transactions!$D$5:$D$504,"Expense")
A22: =Settings!$B$28 | B22: =SUMIFS(Transactions!$E$5:$E$504,Transactions!$C$5:$C$504,A22,Transactions!$D$5:$D$504,"Expense")
A23: =Settings!$B$29 | B23: =SUMIFS(Transactions!$E$5:$E$504,Transactions!$C$5:$C$504,A23,Transactions!$D$5:$D$504,"Expense")
A24: =Settings!$B$30 | B24: =SUMIFS(Transactions!$E$5:$E$504,Transactions!$C$5:$C$504,A24,Transactions!$D$5:$D$504,"Expense")
A25: =Settings!$B$31 | B25: =SUMIFS(Transactions!$E$5:$E$504,Transactions!$C$5:$C$504,A25,Transactions!$D$5:$D$504,"Expense")
A26: =Settings!$B$32 | B26: =SUMIFS(Transactions!$E$5:$E$504,Transactions!$C$5:$C$504,A26,Transactions!$D$5:$D$504,"Expense")
A27: =Settings!$B$33 | B27: =SUMIFS(Transactions!$E$5:$E$504,Transactions!$C$5:$C$504,A27,Transactions!$D$5:$D$504,"Expense")
A28: =Settings!$B$34 | B28: =SUMIFS(Transactions!$E$5:$E$504,Transactions!$C$5:$C$504,A28,Transactions!$D$5:$D$504,"Expense")
A32: Income source | B32: All-time
A33: =Settings!$B$21 | B33: =SUMIFS(Transactions!$E$5:$E$504,Transactions!$C$5:$C$504,A33,Transactions!$D$5:$D$504,"Income")
A34: =Settings!$B$22 | B34: =SUMIFS(Transactions!$E$5:$E$504,Transactions!$C$5:$C$504,A34,Transactions!$D$5:$D$504,"Income")
A35: =Settings!$B$23 | B35: =SUMIFS(Transactions!$E$5:$E$504,Transactions!$C$5:$C$504,A35,Transactions!$D$5:$D$504,"Income")
A36: =Settings!$B$24 | B36: =SUMIFS(Transactions!$E$5:$E$504,Transactions!$C$5:$C$504,A36,Transactions!$D$5:$D$504,"Income")
A37: =Settings!$B$25 | B37: =SUMIFS(Transactions!$E$5:$E$504,Transactions!$C$5:$C$504,A37,Transactions!$D$5:$D$504,"Income")
A38: =Settings!$B$26 | B38: =SUMIFS(Transactions!$E$5:$E$504,Transactions!$C$5:$C$504,A38,Transactions!$D$5:$D$504,"Income")
